[{"name":"sql.active_record","payload":{"sql":"              SELECT a.attname, format_type(a.atttypid, a.atttypmod),\n                     pg_get_expr(d.adbin, d.adrelid), a.attnotnull, a.atttypid, a.atttypmod\n                FROM pg_attribute a LEFT JOIN pg_attrdef d\n                  ON a.attrelid = d.adrelid AND a.attnum = d.adnum\n               WHERE a.attrelid = '\"students\"'::regclass\n                 AND a.attnum \u003e 0 AND NOT a.attisdropped\n               ORDER BY a.attnum\n","name":"SCHEMA","connection_id":49842860,"statement_name":null,"binds":[],"line":18,"filename":"/media/rafaelrf/Dados/projetos/proficiency-test/app/controllers/students_controller.rb","method":"new"},"time":"2015-05-24T12:15:08.011-03:00","transaction_id":"9963fc7e732974c4e8a5","end":"2015-05-24T12:15:08.011-03:00","children":[],"duration":0.8498060000000001},{"name":"sql.active_record","payload":{"sql":"              SELECT COUNT(*)\n              FROM pg_class c\n              LEFT JOIN pg_namespace n ON n.oid = c.relnamespace\n              WHERE c.relkind in ('v','r')\n              AND c.relname = 'students'\n              AND n.nspname = ANY (current_schemas(false))\n","name":"SCHEMA","connection_id":49842860,"statement_name":null,"binds":[],"line":18,"filename":"/media/rafaelrf/Dados/projetos/proficiency-test/app/controllers/students_controller.rb","method":"new"},"time":"2015-05-24T12:15:08.014-03:00","transaction_id":"9963fc7e732974c4e8a5","end":"2015-05-24T12:15:08.014-03:00","children":[],"duration":0.570127},{"name":"sql.active_record","payload":{"sql":"            SELECT attr.attname\n            FROM pg_attribute attr\n            INNER JOIN pg_constraint cons ON attr.attrelid = cons.conrelid AND attr.attnum = cons.conkey[1]\n            WHERE cons.contype = 'p'\n              AND cons.conrelid = '\"students\"'::regclass\n","name":"SCHEMA","connection_id":49842860,"statement_name":null,"binds":[],"line":18,"filename":"/media/rafaelrf/Dados/projetos/proficiency-test/app/controllers/students_controller.rb","method":"new"},"time":"2015-05-24T12:15:08.017-03:00","transaction_id":"9963fc7e732974c4e8a5","end":"2015-05-24T12:15:08.017-03:00","children":[],"duration":0.505466},{"name":"render_partial.action_view","payload":{"identifier":"/media/rafaelrf/Dados/projetos/proficiency-test/app/views/students/_form.html.erb"},"time":"2015-05-24T12:15:08.036-03:00","transaction_id":"bca1d0fc738b6b9a916f","end":"2015-05-24T12:15:08.036-03:00","children":[],"duration":0.7588990000000001},{"name":"render_template.action_view","payload":{"identifier":"/media/rafaelrf/Dados/projetos/proficiency-test/app/views/students/new.html.erb","layout":"layouts/application"},"time":"2015-05-24T12:15:08.031-03:00","transaction_id":"bca1d0fc738b6b9a916f","end":"2015-05-24T12:15:08.037-03:00","children":[],"duration":5.373978},{"name":"process_action.action_controller","payload":{"controller":"StudentsController","action":"new","params":{"action":"new","controller":"students"},"format":"html","method":"GET","path":"/students/new","status":200,"view_runtime":145.336382,"db_runtime":1.885062},"time":"2015-05-24T12:15:08.006-03:00","transaction_id":"bca1d0fc738b6b9a916f","end":"2015-05-24T12:15:08.165-03:00","children":[],"duration":158.919881}]